kitsune/__init__.py
kitsune/client.py
kitsune/values.py
kitsune.py-0.0.1a0.dist-info/METADATA
kitsune.py-0.0.1a0.dist-info/WHEEL
kitsune.py-0.0.1a0.dist-info/top_level.txt
kitsune.py-0.0.1a0.dist-info/RECORD
